dmatrix2np/__init__.py
dmatrix2np/common.py
dmatrix2np/dmatrix_stream_parser.py
dmatrix2np/dmatrix_to_numpy.py
dmatrix2np/dmatrix_v_0_80_stream_parser.py
dmatrix2np/dmatrix_v_1_0_0_stream_parser.py
dmatrix2np/exceptions.py
dmatrix2np-1.0.4.dist-info/LICENSE
dmatrix2np-1.0.4.dist-info/WHEEL
dmatrix2np-1.0.4.dist-info/METADATA
dmatrix2np-1.0.4.dist-info/RECORD
